{
  "name": "Ring",
  "docs": "https://github.com/UniversalDevicesInc/ring-nodeserver",
  "type": "node",
  "executable": "nodeserver.js",
  "install_cloud": "install_cloud.sh",
  "description": "Ring NodeServer",
  "notice": "",
  "shortPoll": "300",
  "longPoll": "14400",
  "profile_version": "1.0.0",
  "ingress_required": true,
  "httpsIngress": true,
  "credits": [
    {
      "title": "Ring NodeServer",
      "author": "Benoit Mercier",
      "version": "1.0.0",
      "date": "May 28th, 2019",
      "source": "https://github.com/UniversalDevicesInc/ring-nodeserver",
      "license": "MIT"
    }
  ]
}
